scrapy_prometheus_exporter
