Metadata-Version: 1.1
Name: scrapy-prometheus-exporter
Version: 1.0.2
Summary: Scrapy extension to export stats to Prometheus
Home-page: https://github.com/rangertaha/scrapy-prometheus-exporter
Author: rangertaha
Author-email: rangertaha@gmail.com
License: MIT
Platform: UNKNOWN
Classifier: Framework :: Scrapy
Classifier: Development Status :: 4 - Beta
Classifier: Environment :: Console
Classifier: Intended Audience :: Developers
Classifier: License :: OSI Approved :: BSD License
Classifier: Operating System :: OS Independent
Classifier: Programming Language :: Python
Classifier: Programming Language :: Python :: 2
Classifier: Programming Language :: Python :: 2.7
Classifier: Topic :: Internet :: WWW/HTTP
